stopwatch/__init__.py
stopwatch/logger.py
stopwatch/statistics.py
stopwatch/stopwatch.py
stopwatch/utils.py
stopwatch/contextmanagers/__init__.py
stopwatch/contextmanagers/profile.py
stopwatch/contextmanagers/stopwatch.py
python_stopwatch-1.1.11.dist-info/LICENSE
python_stopwatch-1.1.11.dist-info/METADATA
python_stopwatch-1.1.11.dist-info/WHEEL
python_stopwatch-1.1.11.dist-info/top_level.txt
python_stopwatch-1.1.11.dist-info/RECORD
