Metadata-Version: 2.1
Name: python-stopwatch
Version: 1.1.11
Summary: A simple stopwatch for measuring code performance
Home-page: https://github.com/jonghwanhyeon/python-stopwatch
Author: Jonghwan Hyeon
Author-email: jonghwanhyeon93@gmail.com
License: MIT
Keywords: stopwatch,profile
Classifier: Development Status :: 4 - Beta
Classifier: Intended Audience :: Developers
Classifier: License :: OSI Approved :: MIT License
Classifier: Programming Language :: Python :: 3
Classifier: Programming Language :: Python :: 3 :: Only
Requires-Python: >=3.7
License-File: LICENSE
Requires-Dist: python-tml
Requires-Dist: typing-extensions
